inplace_restarter/__init__.py
inplace_restarter/__main__.py
inplace_restarter/py.types
inplace_restarter-0.1.0.dist-info/LICENSE
inplace_restarter-0.1.0.dist-info/WHEEL
inplace_restarter-0.1.0.dist-info/METADATA
inplace_restarter-0.1.0.dist-info/RECORD
