Metadata-Version: 2.1
Name: inplace_restarter
Version: 0.1.0
Summary: A Kernel Proxy to restart your kernels in place.
Home-page: https://github.com/Carreau/inplace_restarter/
Author: Matthias Bussonnier
Author-email: bussonniermatthias@gmail.com
Classifier: License :: OSI Approved :: MIT License
Requires-Dist: ipykernel
